uberduck/__init__.py
uberduck/classes.py
uberduck/main.py
uberduck-0.0.1.dist-info/LICENSE
uberduck-0.0.1.dist-info/METADATA
uberduck-0.0.1.dist-info/WHEEL
uberduck-0.0.1.dist-info/top_level.txt
uberduck-0.0.1.dist-info/RECORD
