Metadata-Version: 2.1
Name: uberduck
Version: 0.0.1
Summary: A synchronous and asynchronous API wrapper for the UberDuck text-to-speech service (https://uberduck.ai) with 100% coverage and top-notch utilities.
Home-page: https://github.com/ImNimboss/uberduck
Author: ImNimboss
Author-email: contact@nimboss.me
License: MIT
Project-URL: Documentation, https://github.com/ImNimboss/uberduck/tree/main/Documentation
Project-URL: Issue Tracker, https://github.com/ImNimboss/uberduck/issues
Project-URL: Source, https://github.com/ImNimboss/uberduck
Project-URL: Funding, https://patreon.com/nimboss
Project-URL: API Credits, https://uberduck.ai
Project-URL: Creator, https://nimboss.me
Project-URL: Discord, https://discord.gg/FcxqdJ7AQq
Project-URL: Repository, https://github.com/ImNimboss/uberduck
Keywords: uberduck,wrapper,api,text-to-speech,async,famous,tts,texttospeech,AI,api-wrapper,api-key,api-secret
Platform: UNKNOWN
Classifier: Development Status :: 5 - Production/Stable
Classifier: Intended Audience :: Developers
Classifier: License :: OSI Approved :: MIT License
Classifier: Natural Language :: English
Classifier: Operating System :: OS Independent
Classifier: Programming Language :: Python :: 3
Classifier: Programming Language :: Python :: 3.6
Classifier: Programming Language :: Python :: 3.7
Classifier: Programming Language :: Python :: 3.8
Classifier: Programming Language :: Python :: 3.9
Classifier: Programming Language :: Python :: 3.10
Classifier: Programming Language :: Python :: Implementation :: CPython
Classifier: Topic :: Artistic Software
Classifier: Topic :: Games/Entertainment
Classifier: Topic :: Internet
Classifier: Topic :: Internet :: WWW/HTTP
Classifier: Topic :: Internet :: WWW/HTTP :: Dynamic Content
Classifier: Topic :: Multimedia :: Sound/Audio
Classifier: Topic :: Multimedia :: Sound/Audio :: Players
Classifier: Topic :: Multimedia :: Sound/Audio :: Speech
Classifier: Topic :: Scientific/Engineering :: Artificial Intelligence
Classifier: Topic :: Software Development
Classifier: Topic :: Software Development :: Libraries
Classifier: Topic :: Software Development :: Libraries :: Python Modules
Classifier: Topic :: Utilities
Requires-Python: >=3.6.0
Requires-Dist: requests
Requires-Dist: aiohttp
Requires-Dist: polling
Requires-Dist: pydub
